evolutionhttp/__init__.py
evolutionhttp/client.py
evolutionhttp/local_client.py
evolutionhttp-0.0.19.dist-info/METADATA
evolutionhttp-0.0.19.dist-info/WHEEL
evolutionhttp-0.0.19.dist-info/licenses/LICENSE
evolutionhttp-0.0.19.dist-info/RECORD
