Metadata-Version: 2.4
Name: evolutionhttp
Version: 0.0.19
Summary: An HTTP client for controlling a Bryant Evolution HVAC system
Project-URL: Homepage, https://github.com/danielsmyers/evolutionhttp
Project-URL: Issues, https://github.com/danielsmyers/evolutionhttp/issues
Author-email: Daniel Myers <danielsmyers@gmail.com>
License-File: LICENSE
Classifier: License :: OSI Approved :: Apache Software License
Classifier: Operating System :: OS Independent
Classifier: Programming Language :: Python :: 3
Requires-Python: >=3.12
